Workbook

Sheet Run Notes
B2: RUN NOTES
B4: Source file
B5: Periods
B6: Status
B7: Accounts mapped
B8: Calculation policy
B9: Notes

Sheet COA
B2: COA_ID | W2: MAPPED LABELS | X2: MODEL FEEDBACK | Y2: VENUE NAME
B3: S12.rooms_available
B4: S12.rooms_sold
B5: S12.occupancy
B6: S12.adr
B7: S12.revpar
B8: S12.total_rooms_revenue
B9: S12.total_food_and_beverage_revenue
B10: S12.total_other_operated_departments_revenue
B11: S12.total_miscellaneous_income
B12: S12.total_revenue
B13: S12.total_rooms_expenses
B14: S12.total_food_and_beverage_expenses
... B273: S11.total_non_operating_income_and_expenses

Sheet KHP Model Accounts
B14: KHP UNDERWRITING MODEL INPUTS
C17: =COA!C2 -> 0
B19: Keys | C19: =C20/365 -> 0
B20: Rooms Available | C20: =COA!C3 -> 0
B21: Rooms Sold | C21: =COA!C4 -> 0
B29: Occupancy | C29: =COA!C5 -> 0
B30: ADR | C30: =COA!C6 -> 0
B31: RevPAR | C31: =C29*C30 -> 0
B32: Total RevPAR | C32: =C61/C20 -> #DIV/0!
B33: GOPAR | C33: =C217/C20 -> #DIV/0!
B35: Revenue (POR)
B36: Rooms | C36: =COA!C8 -> 0
B37: Food & Beverage | C37: =SUM(C38:C46) -> 0
B38: Mini Bar | C38: 0
B39: Room Service | C39: =SUM(COA!C97,COA!C112) -> 0
B40: =COA!Y86 -> 0 | C40: =SUM(COA!C86,COA!C101) -> 0
B41: =COA!Y87 -> 0 | C41: =SUM(COA!C87,COA!C102) -> 0
B42: =COA!Y88 -> 0 | C42: =SUM(COA!C88,COA!C103) -> 0
B43: =COA!Y89 -> 0 | C43: =SUM(COA!C89,COA!C104) -> 0
B44: All other F&B Revenue / F&B Allowances | C44: =SUM(COA!C90:C93,COA!C105:C108,COA!C98,COA!C113) -> 0
B45: Banquets | C45: =SUM(COA!C96,COA!C111) -> 0
B46: Other F&B Revenue | C46: =COA!C9-SUM('KHP Model Accounts'!C38:C45) -> 0
B47: Parking | C47: =COA!C146 -> 0
B48: Spa | C48: =SUM(C49:C50) -> 0
B49: Spa Services | C49: =COA!C153-'KHP Model Accounts'!C50 -> 0
B50: Spa Shop | C50: =COA!C151 -> 0
B51: Retail Shop | C51: =COA!C158 -> 0
B52: Other Operated | C52: =SUM(C53:C55) -> 0
B53: Recreation | C53: =COA!C163 -> 0
B54: Golf | C54: =COA!C167 -> 0
B55: All Other OOD | C55: =COA!C10-SUM('KHP Model Accounts'!C53:C54,'KHP Model Accounts'!C47:C48,C51) -> 0
B56: Miscellaneous Income | C56: =SUM(C57:C59) -> 0
B57: Resort Fees | C57: =COA!C174 -> 0
B58: Space Rental | C58: =COA!C175 -> 0
B59: Other Misc. Income | C59: =COA!C11-SUM('KHP Model Accounts'!C57:C58) -> 0
B61: Total Revenue | C61: =SUM(C56,C51:C52,C47:C48,C36:C37) -> 0
B62: Total Revenue (POR) | C62: =C61/C21 -> #DIV/0!
B64: Departmental Expenses
B65: Rooms
B66: Salaries & Wages (POR) | C66: =SUM(COA!C63,COA!C65) -> 0
B67: Payroll Taxes & Employee Benefits (% of S&W) | C67: =C68-C66 -> 0
B68: Total Rooms Payroll (POR) | C68: =COA!C70 -> 0
B69: Travel Agent Commissions (% of Rms. Rev.) | C69: =SUM(COA!C71) -> 0
B70: Reservation Expense (% of Rms. Rev.) | C70: =COA!C82 -> 0
B71: Operating, Cleaning & Guest Supplies (POR) | C71: =COA!C77 -> 0
B72: Complimentary Gifts & Services (POR) | C72: =COA!C72 -> 0
B73: Laundry & Dry Cleaning (POR) | C73: =COA!C78 -> 0
B74: Other Rooms Expense (POR) | C74: =C75-SUM(C69:C73) -> 0
B75: Total Other Rooms Expense (POR) | C75: =COA!C13-'KHP Model Accounts'!C68 -> 0
B76: Total Rooms Expense | C76: =C75+C68 -> 0
B77: Total Rooms Expense % | C77: =C76/C36 -> #DIV/0!
B78: Total Rooms Expense POR | C78: =C76/C20 -> #DIV/0!
B80: Food & Beverage | C80: =SUM(C81:C83) -> 0
B81: F&B Consolidated COGS (%) | C81: =COA!C128 -> 0
B82: F&B Consolidated Payroll (%) | C82: =COA!C143 -> 0
B83: F&B Consolidated Op. Ex. (%) | C83: =COA!C14-SUM('KHP Model Accounts'!C81:C82) -> 0
B84: Mini Bar | C84: =+SUM(C85:C87) -> 0
B85: Mini Bar COGS (%) | C85: 0
B86: Mini Bar Payroll (%) | C86: 0
B87: Mini Bar Op. Ex. (%) | C87: 0
B88: Room Service | C88: =+SUM(C89:C91) -> 0
B89: Room Service COGS (%) | C89: 0
B90: Room Service Payroll (%) | C90: 0
B91: Room Service Op. Ex. (%) | C91: 0
B92: Outlet 1 | C92: =+SUM(C93:C95) -> 0
B93: Outlet 1 COGS (%) | C93: 0
B94: Outlet 1 Payroll (%) | C94: 0
B95: Outlet 1 Op. Ex. (%) | C95: 0
B96: Outlet 2 | C96: =+SUM(C97:C99) -> 0
B97: Outlet 2 COGS (%) | C97: 0
B98: Outlet 2 Payroll (%) | C98: 0
B99: Outlet 2 Op. Ex. (%) | C99: 0
B100: Outlet 3 | C100: =+SUM(C101:C103) -> 0
B101: Outlet 3 COGS (%) | C101: 0
B102: Outlet 3 Payroll (%) | C102: 0
B103: Outlet 3 Op. Ex. (%) | C103: 0
B104: Outlet 4 | C104: =+SUM(C105:C107) -> 0
B105: Outlet 4 COGS (%) | C105: 0
B106: Outlet 4 Payroll (%) | C106: 0
B107: Outlet 4 Op. Ex. (%) | C107: 0
B108: Outlet 5 | C108: =+SUM(C109:C111) -> 0
B109: Outlet 5 COGS (%) | C109: 0
B110: Outlet 5 Payroll (%) | C110: 0
B111: Outlet 5 Op. Ex. (%) | C111: 0
B112: Banquets | C112: =+SUM(C113:C115) -> 0
B113: Banquets COGS (%) | C113: 0
B114: Banquets Payroll (%) | C114: 0
B115: Banquets Op. Ex. (%) | C115: 0
B116: Other F&B Expense | C116: 0
B117: Parking | C117: =SUM(C118:C120) -> 0
B118: Parking COGS (%) | C118: =COA!C147 -> 0
B119: Parking Payroll (%) | C119: =COA!C148 -> 0
B120: Parking Op. Ex. (%) | C120: =COA!C150-SUM('KHP Model Accounts'!C118:C119) -> 0
B121: Spa | C121: =SUM(C122:C124) -> 0
B122: Spa COGS (%) | C122: =COA!C154 -> 0
B123: Spa Payroll (%) | C123: =COA!C155 -> 0
B124: Spa Op. Ex. (%) | C124: =COA!C157-SUM('KHP Model Accounts'!C122:C123) -> 0
B125: Spa Management Fees (%) | C125: 0
B126: Retail Shop | C126: =SUM(C127:C129) -> 0
B127: Retail Shop COGS (%) | C127: =COA!C159 -> 0
...
